erdetect/__init__.py
erdetect/__main__.py
erdetect/_erdetect.py
erdetect/main_cli.py
erdetect/version.py
erdetect/core/__init__.py
erdetect/core/config.py
erdetect/core/detection.py
erdetect/core/peak_finder.py
erdetect/core/metrics/metric_cross_proj.py
erdetect/core/metrics/metric_interface.py
erdetect/core/metrics/metric_waveform.py
erdetect/utils/__init__.py
erdetect/utils/misc.py
erdetect/views/__init__.py
erdetect/views/gui.py
erdetect/views/output_images.py
erdetect-2.6.2.dist-info/LICENSE
erdetect-2.6.2.dist-info/METADATA
erdetect-2.6.2.dist-info/WHEEL
erdetect-2.6.2.dist-info/top_level.txt
erdetect-2.6.2.dist-info/RECORD
