Metadata-Version: 2.2
Name: erdetect
Version: 2.6.2
Summary: A package for the automatic detection of evoked responses in SPES/CCEP data
Author-email: Max van den Boom <m.a.vandenboom84@gmail.com>
License: GPLv3
Project-URL: homepage, https://github.com/MultimodalNeuroimagingLab/ERDetect
Project-URL: documentation, https://github.com/MultimodalNeuroimagingLab/ERDetect
Project-URL: repository, https://github.com/MultimodalNeuroimagingLab/ERDetect
Keywords: evoked response,detection,ieeg,n1,SPES,CCEP
Classifier: Intended Audience :: Science/Research
Classifier: License :: OSI Approved :: GNU General Public License v3 (GPLv3)
Classifier: Operating System :: OS Independent
Classifier: Programming Language :: Python :: 3
Classifier: Programming Language :: Python :: 3 :: Only
Classifier: Programming Language :: Python :: 3.13
Classifier: Programming Language :: Python :: 3.12
Classifier: Programming Language :: Python :: 3.11
Classifier: Programming Language :: Python :: 3.10
Classifier: Programming Language :: Python :: 3.9
Classifier: Topic :: Scientific/Engineering
Requires-Python: >=3.9
License-File: LICENSE
Requires-Dist: ieegprep>=1.6.1
Requires-Dist: numpy>=2.2.1
Requires-Dist: scipy>=1.15.0
Requires-Dist: matplotlib>=3.10.0
Requires-Dist: bids_validator>=1.14.6
